magic_sisters_932/__init__.py
magic_sisters_932/actions.py
magic_sisters_932/roomie_names.py
test_package/__init__.py
test_package/pip_function_A.py
test_package/pip_function_B.py
magic_sisters_932-0.0.3.dist-info/LICENSE
magic_sisters_932-0.0.3.dist-info/METADATA
magic_sisters_932-0.0.3.dist-info/WHEEL
magic_sisters_932-0.0.3.dist-info/top_level.txt
magic_sisters_932-0.0.3.dist-info/RECORD
